setup.py
django_url_redirect.egg-info/PKG-INFO
django_url_redirect.egg-info/SOURCES.txt
django_url_redirect.egg-info/dependency_links.txt
django_url_redirect.egg-info/requires.txt
django_url_redirect.egg-info/top_level.txt
url_redirect/__init__.py
url_redirect/middleware.py