Metadata-Version: 1.0
Name: django-url-redirect
Version: 0.1.0
Summary: Simple redirect middleware for Django
Home-page: https://github.com/gizmag/django-url-redirect/
Author: Gizmag
Author-email: tech@gizmag.com
License: UNKNOWN
Platform: UNKNOWN
